factanal/__init__.py
factanal/wrapper.py
factanal-0.2.0.dist-info/LICENSE
factanal-0.2.0.dist-info/METADATA
factanal-0.2.0.dist-info/WHEEL
factanal-0.2.0.dist-info/top_level.txt
factanal-0.2.0.dist-info/RECORD
