Metadata-Version: 2.1
Name: factanal
Version: 0.2.0
Summary: A python wrapper for the R function factanal.
Home-page: https://github.com/kjul/factanalpy
Author: kjul
Author-email: juliankunschke@yahoo.de
License: MIT
Platform: UNKNOWN
Classifier: License :: OSI Approved :: MIT License
Classifier: Programming Language :: Python :: 3
Classifier: Programming Language :: Python :: 3.8
Requires-Dist: rpy2
